dataset_manager/__init__.py
dataset_manager/dataset_manager.py
s3_manager/__init__.py
s3_manager/s3_manager.py
llmassist-0.1.0.dist-info/METADATA
llmassist-0.1.0.dist-info/WHEEL
llmassist-0.1.0.dist-info/top_level.txt
llmassist-0.1.0.dist-info/RECORD
