Metadata-Version: 2.1
Name: llmassist
Version: 0.1.0
Summary: A easy assist package for Large Language model inference and fine-tuning.
Author: Yinghao Li
Author-email: shiyi.yinghao@gmail.com
Requires-Python: >=3.11
